reedwolf/entities/__init__.py
reedwolf/entities/apply.py
reedwolf/entities/attr_nodes.py
reedwolf/entities/base.py
reedwolf/entities/bound_models.py
reedwolf/entities/config.py
reedwolf/entities/containers.py
reedwolf/entities/contexts.py
reedwolf/entities/eval_base.py
reedwolf/entities/eval_children.py
reedwolf/entities/eval_field.py
reedwolf/entities/eval_items.py
reedwolf/entities/exceptions.py
reedwolf/entities/expression_evaluators.py
reedwolf/entities/expressions.py
reedwolf/entities/fields.py
reedwolf/entities/func_args.py
reedwolf/entities/func_builtin.py
reedwolf/entities/functions.py
reedwolf/entities/load.py
reedwolf/entities/meta.py
reedwolf/entities/namespaces.py
reedwolf/entities/registries.py
reedwolf/entities/setup.py
reedwolf/entities/utils.py
reedwolf/entities/valid_base.py
reedwolf/entities/valid_children.py
reedwolf/entities/valid_field.py
reedwolf/entities/valid_items.py
reedwolf.entities-0.7.0.dist-info/LICENSE
reedwolf.entities-0.7.0.dist-info/METADATA
reedwolf.entities-0.7.0.dist-info/WHEEL
reedwolf.entities-0.7.0.dist-info/top_level.txt
reedwolf.entities-0.7.0.dist-info/RECORD
